officely/CustomException.py
officely/__init__.py
officely/generator.py
officely/main.py
officely/run.py
officely/stream_handler.py
OfficelyTestTeam2-0.1.4.dist-info/LICENSE
OfficelyTestTeam2-0.1.4.dist-info/METADATA
OfficelyTestTeam2-0.1.4.dist-info/WHEEL
OfficelyTestTeam2-0.1.4.dist-info/top_level.txt
OfficelyTestTeam2-0.1.4.dist-info/RECORD
