Metadata-Version: 2.1
Name: OfficelyTestTeam2
Version: 0.1.4
Summary: A brief description of your package
Author: Your Name
Author-email: your.email@example.com
Classifier: Programming Language :: Python :: 3
Classifier: License :: OSI Approved :: MIT License
Classifier: Operating System :: OS Independent
Requires-Python: >=3.8
License-File: LICENSE
